{
    "model_name": "gradient_boosting_balanced_clean_elo",
    "model_path": "models/current_best_model_with_elo.pkl",
    "training_data": "data/processed/matchup_training_data_with_clean_elo.csv",
    "features": [
        "last_5_points_per_match_diff",
        "last_5_goals_for_per_match_diff",
        "last_5_goals_against_per_match_diff",
        "last_5_goal_difference_per_match_diff",
        "last_5_win_diff",
        "last_5_draw_diff",
        "last_5_loss_diff",
        "elo_diff"
    ],
    "target": "target",
    "train_cutoff": "2018-01-01",
    "class_labels": [
        "draw",
        "loss",
        "win"
    ],
    "metrics": {
        "model": "gradient_boosting_balanced_clean_elo",
        "accuracy": 0.568865239450563,
        "macro_f1": 0.5278087352947648,
        "weighted_f1": 0.5709447686699852,
        "win_f1": 0.6876155268022182,
        "draw_f1": 0.3090717299578059,
        "loss_f1": 0.5867389491242703,
        "predicted_wins": 3714,
        "predicted_draws": 1930,
        "predicted_losses": 2437
    }
}